MANIFEST.in
README.md
setup.py
django_rating.egg-info/PKG-INFO
django_rating.egg-info/SOURCES.txt
django_rating.egg-info/dependency_links.txt
django_rating.egg-info/top_level.txt
rating/__init__.py
rating/admin.py
rating/apps.py
rating/models.py
rating/rating_values.py
rating/serializers.py
rating/tests.py
rating/urls.py
rating/views.py
rating/migrations/0001_initial.py
rating/migrations/__init__.py