Metadata-Version: 2.1
Name: django-rating
Version: 0.1.4
Summary: A simple Django app to handle object ratings.
Home-page: https://www.github.com/pulilab/django-rating
Author: Pulilab
Author-email: bh@pulilab.com
License: BSD License
Platform: UNKNOWN
Classifier: Environment :: Web Environment
Classifier: Framework :: Django
Classifier: Framework :: Django :: 2.1
Classifier: Intended Audience :: Developers
Classifier: License :: OSI Approved :: BSD License
Classifier: Operating System :: OS Independent
Classifier: Programming Language :: Python
Classifier: Programming Language :: Python :: 3.7
Classifier: Topic :: Internet :: WWW/HTTP
